{
    "Version": "1.2",
    "Data": {
        "Source": "d:\\unreal\\udemy\\obstacle-assault\\obstacleassault\\source\\obstacleassault\\obstacleassault.cpp",
        "ProvidedModule": "",
        "PCH": "d:\\unreal\\udemy\\obstacle-assault\\obstacleassault\\intermediate\\build\\win64\\x64\\obstacleassaulteditor\\development\\unrealed\\sharedpch.unrealed.project.valapi.cpp20.h.pch",
        "Includes": [
            "d:\\unreal\\udemy\\obstacle-assault\\obstacleassault\\intermediate\\build\\win64\\x64\\unrealeditor\\development\\obstacleassault\\definitions.obstacleassault.h",
            "d:\\unreal\\udemy\\obstacle-assault\\obstacleassault\\source\\obstacleassault\\obstacleassault.h"
        ],
        "ImportedModules": [],
        "ImportedHeaderUnits": []
    }
}